{
  "main": {
    "id": "22e6f5d40891cba8",
    "type": "split",
    "children": [
      {
        "id": "9c6eaf861776aa87",
        "type": "tabs",
        "children": [
          {
            "id": "3075cffdd6ed08c7",
            "type": "leaf",
            "state": {
              "type": "excalidraw",
              "state": {
                "file": "Notatki/Teoria systemów/Ćwiczenia/Ćwiczenia 6/Drawing 2023-05-22 07.33.21.excalidraw.md"
              }
            }
          },
          {
            "id": "fc7869c466adad70",
            "type": "leaf",
            "state": {
              "type": "excalidraw",
              "state": {
                "file": "Notatki/Algebra liniowa 2/Wykłady/Wykład 5/Drawing 2023-05-17 13.23.01.excalidraw.md"
              }
            }
          }
        ],
        "currentTab": 1
      }
    ],
    "direction": "vertical"
  },
  "left": {
    "id": "78e6d1bb01ac3ce5",
    "type": "split",
    "children": [
      {
        "id": "32fb0c37e4238e8b",
        "type": "tabs",
        "children": [
          {
            "id": "ecd815a6ba5683a0",
            "type": "leaf",
            "state": {
              "type": "file-explorer",
              "state": {
                "sortOrder": "alphabetical"
              }
            }
          },
          {
            "id": "840e85c7e4b09b54",
            "type": "leaf",
            "state": {
              "type": "search",
              "state": {
                "query": "",
                "matchingCase": true,
                "explainSearch": false,
                "collapseAll": false,
                "extraContext": false,
                "sortOrder": "alphabetical"
              }
            }
          },
          {
            "id": "d90a90b825171ac3",
            "type": "leaf",
            "state": {
              "type": "bookmarks",
              "state": {}
            }
          }
        ]
      }
    ],
    "direction": "horizontal",
    "width": 313.5069465637207
  },
  "right": {
    "id": "9e90e398a7031783",
    "type": "split",
    "children": [
      {
        "id": "01e3dc24875e4766",
        "type": "tabs",
        "children": [
          {
            "id": "63e4c1a5f04bc183",
            "type": "leaf",
            "state": {
              "type": "tag",
              "state": {
                "sortOrder": "frequency",
                "useHierarchy": false
              }
            }
          },
          {
            "id": "0f01b4308a0bf430",
            "type": "leaf",
            "state": {
              "type": "advanced-tables-toolbar",
              "state": {}
            }
          },
          {
            "id": "513706df279c3801",
            "type": "leaf",
            "state": {
              "type": "outgoing-link",
              "state": {
                "file": "Notatki/Algebra liniowa 2/Wykłady/Wykład 5/Drawing 2023-05-17 13.23.01.excalidraw.md",
                "linksCollapsed": false,
                "unlinkedCollapsed": true
              }
            }
          },
          {
            "id": "972bc58ecad3fd93",
            "type": "leaf",
            "state": {
              "type": "outline",
              "state": {
                "file": "Notatki/Algebra liniowa 2/Wykłady/Wykład 5/Drawing 2023-05-17 13.23.01.excalidraw.md"
              }
            }
          }
        ],
        "currentTab": 3
      }
    ],
    "direction": "horizontal",
    "width": 327.5,
    "collapsed": true
  },
  "left-ribbon": {
    "hiddenItems": {
      "templates:Insert template": false,
      "graph:Open graph view": false,
      "canvas:Create new canvas": false,
      "command-palette:Open command palette": false,
      "table-editor-obsidian:Advanced Tables Toolbar": false,
      "obsidian-full-calendar:Open Full Calendar": false,
      "obsidian-excalidraw-plugin:Create new drawing": false
    }
  },
  "active": "fc7869c466adad70",
  "lastOpenFiles": [
    "Notatki/Algebra liniowa 2/Wykłady/Wykład 5/Drawing 2023-05-24 13.21.00.excalidraw.md",
    "Notatki/Algebra liniowa 2/Wykłady/Wykład 6/Drawing 2023-05-24 13.33.14.excalidraw.md",
    "Notatki/Algebra liniowa 2/Wykłady/Wykład 5/Drawing 2023-05-17 13.23.01.excalidraw.md",
    "Notatki/Algebra liniowa 2/Wykłady/Wykład 5/Drawing 2023-05-16 08.08.53.excalidraw.md",
    "Notatki/Teoria systemów/Ćwiczenia/Ćwiczenia 6/Drawing 2023-05-22 07.33.21.excalidraw.md",
    "Notatki/Algebra liniowa 2/Wykłady/Wykład 3/Drawing 2023-05-10 13.17.28.excalidraw.md",
    "Notatki/Algebra liniowa 2/Wykłady/Wykład 2/Drawing 2023-04-26 13.23.30.excalidraw.md",
    "Notatki/Algebra liniowa 2/Wykłady/Wykład 1/AL2-Wyklad-1.pdf",
    "Notatki/Algebra liniowa 2/Wykłady/Wykład 1/Wyklad_1a.pdf",
    "Notatki/Algebra liniowa 2/Wykłady/Wykład 1/AL2-zestaw-1.pdf",
    "Notatki/Algebra liniowa 2/Wykłady/Wykład 2/AL2-zestaw-2.pdf",
    "Notatki/Algebra liniowa 2/Wykłady/Wykład 2/AL2-Wyklad-2.pdf",
    "Notatki/Algebra liniowa 2/Wykłady/Wykład 1/Drawing 2023-04-19 14.05.45.excalidraw.md",
    "Notatki/Algebra liniowa 2/Wykłady/Wykład 1/Wykład 1.md",
    "Notatki/Teoria systemów/Wykłady/Wykład 7/Wykład 7.md",
    "Notatki/Teoria systemów/Wykłady/Wykład 7/Drawing 2023-05-24 07.31.09.excalidraw.md",
    "Notatki/Teoria systemów/Wykłady/Wykład 7",
    "Notatki/Matematyka dyskretna/Ćwiczenia/Ćwiczenia 9/Pasted Image 20230526134758_464.png",
    "Notatki/Matematyka dyskretna/Ćwiczenia/Ćwiczenia 9/Pasted Image 20230526133509_927.png",
    "Notatki/Matematyka dyskretna/Ćwiczenia/Ćwiczenia 9/Drawing 2023-05-26 14.25.19.excalidraw.md",
    "Notatki/Matematyka dyskretna/Ćwiczenia/Ćwiczenia 9/Drawing 2023-05-26 13.27.16.excalidraw.md",
    "Notatki/Matematyka dyskretna/Ćwiczenia/Ćwiczenia 8/Drawing 2023-05-26 13.15.53.excalidraw.md",
    "Notatki/Fizyka 1.1A/Wykłady/Wykład 8/Drawing 2023-05-30 13.15.22.excalidraw.md",
    "Notatki/Fizyka 1.1A/Wykłady/Wykład 8/Drawing 2023-05-23 13.11.27.excalidraw.md",
    "Notatki/Algebra liniowa 2/Wykłady/Kolos/Kolos.md",
    "Notatki/Algebra liniowa 2/Wykłady/Kolos",
    "Notatki/Teoria systemów/Ćwiczenia/Ćwiczenia 6/Ćwiczenia 6.md",
    "Notatki/Teoria systemów/Ćwiczenia/Ćwiczenia 6/Drawing 2023-05-08 07.32.16.excalidraw.md",
    "Notatki/Teoria systemów/Ćwiczenia/Ćwiczenia 5/Ćwiczenia 5.md",
    "Notatki/Teoria systemów/Ćwiczenia/Ćwiczenia 5/Drawing 2023-05-08 07.32.16.excalidraw.md",
    "Notatki/Teoria systemów/Ćwiczenia/Ćwiczenia 5",
    "Notatki/Teoria systemów/Wykłady/teoria systemów.pdf",
    "Notatki/Teoria systemów/Wykłady/Kolokwium/Kolokwium.md",
    "Notatki/Teoria systemów/Wykłady/Kolokwium",
    "Notatki/Rachunek prawdopodobieństwa/Wykłady/Wykład 6/Drawing 2023-05-18 11.06.37.excalidraw.md",
    "Notatki/Podstawy automatyki i robotyki/Wykłady/Wykład 9/Wykład 9.md",
    "Notatki/Podstawy automatyki i robotyki/Wykłady/Wykład 8/Wykład 8.md",
    "Notatki/Podstawy automatyki i robotyki/Wykłady/Wykład 8/18.05.2023 r. w2(1).png",
    "Notatki/Podstawy automatyki i robotyki/Wykłady/Wykład 8/12.05.2023(1).png",
    "Notatki/Podstawy automatyki i robotyki/Wykłady/Wykład 7/Wykład 7.md",
    "Notatki/Miernictwo w informatyce i telekomunikacji/Labolatoria/Labolatoria 6/Pasted Image 20230513100604_918.png",
    "Notatki/Matematyka dyskretna/Ćwiczenia/Kolokwium 2/Pasted Image 20230511180759_818.png",
    "Notatki/Matematyka dyskretna/Ćwiczenia/Kolokwium 2/Pasted Image 20230511171741_766.png",
    "Notatki/Fizyka 1.1A/Ćwiczenia/Ćwiczenia 4/Pasted Image 20230519123344_296.png",
    "Notatki/Fizyka 1.1A/Ćwiczenia/Ćwiczenia 4/Pasted Image 20230519123034_878.png",
    "Notatki/Fizyka 1.1A/Ćwiczenia/Ćwiczenia 4/Pasted Image 20230518185347_965.png",
    "Untitled.canvas"
  ]
}